{title:'Ares-Gastesi (§71995§r)', author: 'Pablo Ares-Gastesi', display:{Lore:['[{"text": "arXiv:math/9501202", "color": "red"}]']}, pages:['{"text": "\\u00a7n\\u00a72math.GT\\u00a7r, \\u00a72math.AG\\u00a7r, \\u00a72math.DG\\u00a7r\\u00a7r\\n\\u00a76\\u00a7lThe Bers-Greenberg Theorem and the Maskit Embedding for Teichm\\u00fcller spaces\\u00a7r\\n\\n\\u00a78\\u00a7oPablo Ares-Gastesi\\u00a7r\\n\\n\\u00a771995\\u00a7r"}','{"text": "arXiv:\\u00a7c\\u00a7nmath/9501202\\u00a7r\\n\\nVersion:\\u00a77v1 (Sun, 22 Jan 1995 17:09:49 GMT)\\u00a7r\\n\\n"}','{"text": "Comments: \\u00a77\\u00a7o15 pages, plain LaTeX, bf for Bbb, 2 figures in plain LaTeX, hard copies available under request\\u00a7r"}']}
{title:'Gastesi (§71995§r)', author: 'Pablo Arés Gastesi', display:{Lore:['[{"text": "arXiv:math/9502201", "color": "red"}]']}, pages:['{"text": "\\u00a7n\\u00a72math.GT\\u00a7r, \\u00a72math.AG\\u00a7r\\u00a7r\\n\\u00a76\\u00a7lCoordinates for Teichm\\u00fcller spaces of b-groups with torsion\\u00a7r\\n\\n\\u00a78\\u00a7oPablo Ar\\u00e9s Gastesi\\u00a7r\\n\\n\\u00a771995\\u00a7r"}','{"text": "arXiv:\\u00a7c\\u00a7nmath/9502201\\u00a7r\\n\\nJournal reference:\\u00a71\\u00a7nAnnal Acad Scien Fenn A I, 20 (1995) 279-300\\u00a7r\\n\\nVersion:\\u00a77v1 (Wed, 15 Feb 1995 07:57:39 GMT)\\u00a7r\\n\\n"}','{"text": "Comments: \\u00a77\\u00a7oPlain LaTeX, with Bbb subtituted by bf, 19 pgs,65 Kb, additional file with4 figures (2 pgs) in ps form\\u00a7r"}']}
{title:'Gastesi (§71995§r)', author: 'Pablo Arés Gastesi', display:{Lore:['[{"text": "arXiv:math/9502202", "color": "red"}]']}, pages:['{"text": "\\u00a7n\\u00a72math.GT\\u00a7r, \\u00a72math.AG\\u00a7r\\u00a7r\\n\\u00a76\\u00a7lOn Teichm\\u00fcller spaces of Koebe groups\\u00a7r\\n\\n\\u00a78\\u00a7oPablo Ar\\u00e9s Gastesi\\u00a7r\\n\\n\\u00a771995\\u00a7r"}','{"text": "arXiv:\\u00a7c\\u00a7nmath/9502202\\u00a7r\\n\\nVersion:\\u00a77v1 (Fri, 17 Feb 1995 10:46:54 GMT)\\u00a7r\\n\\n"}','{"text": "Comments: \\u00a77\\u00a7oplain LaTeX, with cd.sty 67Kbs, 24 pgs, no figures\\u00a7r"}']}
{title:'Bridgeman (§71995§r)', author: 'Martin Bridgeman', display:{Lore:['[{"text": "arXiv:math/9506209", "color": "red"}]']}, pages:['{"text": "\\u00a7n\\u00a72math.GT\\u00a7r\\u00a7r\\n\\u00a76\\u00a7lBounds on Volume Increase under Dehn Drilling Operations\\u00a7r\\n\\n\\u00a78\\u00a7oMartin Bridgeman\\u00a7r\\n\\n\\u00a771995\\u00a7r"}','{"text": "arXiv:\\u00a7c\\u00a7nmath/9506209\\u00a7r\\n\\nVersion:\\u00a77v1 (Tue, 13 Jun 1995 00:00:00 GMT)\\u00a7r"}']}
{title:'Lee et al. (§71995§r)', author: 'Ronnie Lee; Weiping Li', display:{Lore:['[{"text": "arXiv:math/9506221", "color": "red"}]']}, pages:['{"text": "\\u00a7n\\u00a72math.GT\\u00a7r\\u00a7r\\n\\u00a76\\u00a7lFloer homologies for Lagrangian intersections and instantons\\u00a7r\\n\\n\\u00a78\\u00a7oRonnie Lee\\nWeiping Li\\u00a7r\\n\\n\\u00a771995\\u00a7r"}','{"text": "arXiv:\\u00a7c\\u00a7nmath/9506221\\u00a7r\\n\\nVersion:\\u00a77v1 (Mon, 12 Jun 1995 00:00:00 GMT)\\u00a7r"}']}
{title:'Gastesi (§71995§r)', author: 'Pablo Arés Gastesi', display:{Lore:['[{"text": "arXiv:math/9507207", "color": "red"}]']}, pages:['{"text": "\\u00a7n\\u00a72math.GT\\u00a7r, \\u00a72math.AG\\u00a7r\\u00a7r\\n\\u00a76\\u00a7lSome results on Teichm\\u00fcller spaces of Klein surfaces\\u00a7r\\n\\n\\u00a78\\u00a7oPablo Ar\\u00e9s Gastesi\\u00a7r\\n\\n\\u00a771995\\u00a7r"}','{"text": "arXiv:\\u00a7c\\u00a7nmath/9507207\\u00a7r\\n\\nVersion:\\u00a77v1 (Fri, 21 Jul 1995 05:29:14 GMT)\\u00a7r\\n\\n"}','{"text": "Comments: \\u00a77\\u00a7o18 pgs, diagrams in ps form(original file requires xypic macro), 42 Kbs, 2 pgs of figures, AMSLaTeX\\u00a7r"}']}
{title:'Fenley et al. (§71995§r)', author: 'Sérgio Fenley; Lee Mosher', display:{Lore:['[{"text": "arXiv:math/9507216", "color": "red"}]']}, pages:['{"text": "\\u00a7n\\u00a72math.GT\\u00a7r\\u00a7r\\n\\u00a76\\u00a7lQuasigeodesic Flows in Hyperbolic Three-Manifolds\\u00a7r\\n\\n\\u00a78\\u00a7oS\\u00e9rgio Fenley\\nLee Mosher\\u00a7r\\n\\n\\u00a771995\\u00a7r"}','{"text": "arXiv:\\u00a7c\\u00a7nmath/9507216\\u00a7r\\n\\nVersion:\\u00a77v1 (Tue, 11 Jul 1995 00:00:00 GMT)\\u00a7r"}']}
