{title:'White et al. (§71998§r)', author: 'J. A. White; C. C. Chow; J. Ritt; C. Soto-Trevino; N. Kopell', display:{Lore:['[{"text": "arXiv:q-bio/0309024", "color": "red"}]']}, pages:['{"text": "\\u00a7n\\u00a7bq-bio.NC\\u00a7r\\u00a7r\\n\\u00a76\\u00a7lSynchronization and oscillatory dynamics in heterogeneous mutually inhibited neurons\\u00a7r\\n\\n\\u00a78\\u00a7oJ. A. White\\nC. C. Chow\\nJ. Ritt\\nC. Soto-Trevino\\u00a7r\\n\\n\\u00a771998\\u00a7r"}','{"text": "arXiv:\\u00a7c\\u00a7nq-bio/0309024\\u00a7r\\n\\nVersion:\\u00a77v1 (Wed, 18 Feb 1998 16:36:24 GMT)\\u00a7r\\n\\n"}','{"text": "Comments: \\u00a77\\u00a7o17 pages, 6 figures, Kluwer.sty. Journal of Compuational Neuroscience (in press). Originally submitted to the neuro-sys archive which was never publicly announced (was 9802001)\\u00a7r"}']}
{title:'Chow et al. (§71998§r)', author: 'Carson C. Chow; John A. White; Jason Ritt; Nancy Kopell', display:{Lore:['[{"text": "arXiv:q-bio/0309025", "color": "red"}]']}, pages:['{"text": "\\u00a7n\\u00a7bq-bio.NC\\u00a7r\\u00a7r\\n\\u00a76\\u00a7lFrequency control in synchronized networks of inhibitory neurons\\u00a7r\\n\\n\\u00a78\\u00a7oCarson C. Chow\\nJohn A. White\\nJason Ritt\\u00a7r\\n\\n\\u00a771998\\u00a7r"}','{"text": "arXiv:\\u00a7c\\u00a7nq-bio/0309025\\u00a7r\\n\\nVersion:\\u00a77v1 (Fri, 20 Mar 1998 21:12:18 GMT)\\u00a7r\\n\\n"}','{"text": "Comments: \\u00a77\\u00a7o18 pages, 3 figures, Kluwer.sty. J. Comp. Neurosci. (in press). Originally submitted to the neuro-sys archive which was never publicly announced (was 9803001)\\u00a7r"}']}
{title:'Gershon et al. (§71998§r)', author: 'Ethan D. Gershon; Matthew C. Wiener; Peter E. Latham; Barry J. Richmond', display:{Lore:['[{"text": "arXiv:q-bio/0309026", "color": "red"}]']}, pages:['{"text": "\\u00a7n\\u00a7bq-bio.NC\\u00a7r\\u00a7r\\n\\u00a76\\u00a7lCoding Strategies in Monkey V1 and Inferior Temporal Cortices\\u00a7r\\n\\n\\u00a78\\u00a7oEthan D. Gershon\\nMatthew C. Wiener\\nPeter E. Latham\\u00a7r\\n\\n\\u00a771998\\u00a7r"}','{"text": "arXiv:\\u00a7c\\u00a7nq-bio/0309026\\u00a7r\\n\\nJournal reference:\\u00a71\\u00a7nJ. Neurophsysiol. 79: 1135-1144, 1998\\u00a7r\\n\\nVersion:\\u00a77v1 (Thu, 9 Apr 1998 21:25:33 GMT)\\u00a7r\\n\\n"}','{"text": "Comments: \\u00a77\\u00a7o25 pages, 8 figures. Originally submitted to the neuro-sys archive which was never publicly announced (was 9804001)\\u00a7r"}']}
{title:'Depireux et al. (§71998§r)', author: 'Didier A. Depireux; Jonathan Z. Simon; Shihab A. Shamma', display:{Lore:['[{"text": "arXiv:q-bio/0309027", "color": "red"}]']}, pages:['{"text": "\\u00a7n\\u00a7bq-bio.NC\\u00a7r\\u00a7r\\n\\u00a76\\u00a7lMeasuring the dynamics of neural responses in primary auditory cortex\\u00a7r\\n\\n\\u00a78\\u00a7oDidier A. Depireux\\nJonathan Z. Simon\\nShihab A. Shamma\\u00a7r\\n\\n\\u00a771998\\u00a7r"}','{"text": "arXiv:\\u00a7c\\u00a7nq-bio/0309027\\u00a7r\\n\\nVersion:\\u00a77v1 (Thu, 16 Apr 1998 19:23:54 GMT)\\u00a7r\\n\\n"}','{"text": "Comments: \\u00a77\\u00a7o27 pages, 17 figures, straight LaTeX +psfig. Originally submitted to the neuro-sys archive which was never publicly announced (was 9804002)\\u00a7r"}']}
{title:'Mitra et al. (§71998§r)', author: 'P. P. Mitra; B. Pesaran', display:{Lore:['[{"text": "arXiv:q-bio/0309028", "color": "red"}]']}, pages:['{"text": "\\u00a7n\\u00a7bq-bio.NC\\u00a7r, \\u00a7bq-bio.QM\\u00a7r\\u00a7r\\n\\u00a76\\u00a7lAnalysis of Dynamic Brain Imaging Data\\u00a7r\\n\\n\\u00a78\\u00a7oP. P. Mitra\\nB. Pesaran\\u00a7r\\n\\n\\u00a771998\\u00a7r"}','{"text": "arXiv:\\u00a7c\\u00a7nq-bio/0309028\\u00a7r\\n\\nDOI:\\u00a76\\u00a7n10.1016/S0006-3495(99)77236-X\\u00a7r\\n\\nVersion:\\u00a77v1 (Mon, 20 Apr 1998 21:02:27 GMT)\\u00a7r\\n\\n"}','{"text": "Comments: \\u00a77\\u00a7o40 pages; 26 figures with subparts including 3 figures as .gif files. Originally submitted to the neuro-sys archive which was never publicly announced (was 9804003)\\u00a7r"}']}
{title:'Schmidt et al. (§71998§r)', author: 'David M. Schmidt; John S. George; C. C. Wood', display:{Lore:['[{"text": "arXiv:q-bio/0309029", "color": "red"}]']}, pages:['{"text": "\\u00a7n\\u00a7bq-bio.NC\\u00a7r, \\u00a7bq-bio.QM\\u00a7r\\u00a7r\\n\\u00a76\\u00a7lBayesian Inference Applied to the Electromagnetic Inverse Problem\\u00a7r\\n\\n\\u00a78\\u00a7oDavid M. Schmidt\\nJohn S. George\\nC. C. Wood\\u00a7r\\n\\n\\u00a771998\\u00a7r"}','{"text": "arXiv:\\u00a7c\\u00a7nq-bio/0309029\\u00a7r\\n\\nVersion:\\u00a77v1 (Tue, 16 Jun 1998 23:56:12 GMT)\\u00a7r\\n\\n"}','{"text": "Comments: \\u00a77\\u00a7o11 pages, 16 figures, pdf, submitted to Human Brain Mapping, color figures at http://stella.lanl.gov/bi.html. Originally submitted to the neuro-sys archive which was never publicly announced (was 9806001)\\u00a7r"}']}
{title:'Manwani et al. (§71998§r)', author: 'A. Manwani; C. Koch', display:{Lore:['[{"text": "arXiv:q-bio/0309030", "color": "red"}]']}, pages:['{"text": "\\u00a7n\\u00a7bq-bio.NC\\u00a7r\\u00a7r\\n\\u00a76\\u00a7lSynaptic Transmission: An Information-Theoretic Perspective\\u00a7r\\n\\n\\u00a78\\u00a7oA. Manwani\\nC. Koch\\u00a7r\\n\\n\\u00a771998\\u00a7r"}','{"text": "arXiv:\\u00a7c\\u00a7nq-bio/0309030\\u00a7r\\n\\nJournal reference:\\u00a71\\u00a7nAdvances in Neural Information Processing Systems 10, Michael I.\\n  Jordan, Michael J. Kearns and Sara Solla (eds.), 1997\\u00a7r\\n\\nVersion:\\u00a77v1 (Tue, 22 Sep 1998 20:07:14 GMT)\\u00a7r\\n\\n"}','{"text": "Comments: \\u00a77\\u00a7o7 pages, 4 figures, NIPS97 proceedings: neuroscience. Originally submitted to the neuro-sys archive which was never publicly announced (was 9809002)\\u00a7r"}']}
{title:'Victor et al. (§71998§r)', author: 'Jonathan D. Victor; Keith P. Purpura', display:{Lore:['[{"text": "arXiv:q-bio/0309031", "color": "red"}]']}, pages:['{"text": "\\u00a7n\\u00a7bq-bio.NC\\u00a7r, \\u00a7bq-bio.QM\\u00a7r\\u00a7r\\n\\u00a76\\u00a7lMetric-space analysis of spike trains: theory, algorithms, and application\\u00a7r\\n\\n\\u00a78\\u00a7oJonathan D. Victor\\nKeith P. Purpura\\u00a7r\\n\\n\\u00a771998\\u00a7r"}','{"text": "arXiv:\\u00a7c\\u00a7nq-bio/0309031\\u00a7r\\n\\nJournal reference:\\u00a71\\u00a7nNetwork 8, 127-164 (1997)\\u00a7r\\n\\nVersion:\\u00a77v1 (Fri, 30 Oct 1998 22:20:10 GMT)\\u00a7r\\n\\n"}','{"text": "Comments: \\u00a77\\u00a7o16 Figures (not in this file).Originally submitted to the neuro-sys archive which was never publicly announced (was 9810001)\\u00a7r"}']}
{title:'Reich et al. (§71998§r)', author: 'Daniel S. Reich; Jonathan D. Victor; Bruce W. Knight', display:{Lore:['[{"text": "arXiv:q-bio/0309032", "color": "red"}]']}, pages:['{"text": "\\u00a7n\\u00a7bq-bio.NC\\u00a7r, \\u00a7bq-bio.QM\\u00a7r\\u00a7r\\n\\u00a76\\u00a7lThe power ratio and the interval map: spiking models and extracellular data\\u00a7r\\n\\n\\u00a78\\u00a7oDaniel S. Reich\\nJonathan D. Victor\\nBruce W. Knight\\u00a7r\\n\\n\\u00a771998\\u00a7r"}','{"text": "arXiv:\\u00a7c\\u00a7nq-bio/0309032\\u00a7r\\n\\nVersion:\\u00a77v1 (Sun, 1 Nov 1998 16:17:56 GMT)\\u00a7r\\n\\n"}','{"text": "Comments: \\u00a77\\u00a7o2 Tables, 9 Figures. To appear in J. Neurosci. 18 (1998). Originally submitted to the neuro-sys archive which was never publicly announced (was 9905002)\\u00a7r"}']}
